savetomongo/__init__.py
savetomongo/save_mongo.py
savetomongo-0.0.6.dist-info/LICENSE
savetomongo-0.0.6.dist-info/METADATA
savetomongo-0.0.6.dist-info/WHEEL
savetomongo-0.0.6.dist-info/top_level.txt
savetomongo-0.0.6.dist-info/RECORD
